pandas_sqlite3/__init__.py
pandas_sqlite3/pandas_query.py
pandas_sqlite3-0.1.0.dist-info/LICENSE
pandas_sqlite3-0.1.0.dist-info/WHEEL
pandas_sqlite3-0.1.0.dist-info/METADATA
pandas_sqlite3-0.1.0.dist-info/RECORD
