Metadata-Version: 2.1
Name: pandas-sqlite3
Version: 0.1.0
Summary: 
Author: hamilton
Author-email: hamilton@pattern.com
Requires-Python: >=3.8
Classifier: Programming Language :: Python :: 3
Classifier: Programming Language :: Python :: 3.8
Classifier: Programming Language :: Python :: 3.9
Classifier: Programming Language :: Python :: 3.10
Classifier: Programming Language :: Python :: 3.11
Requires-Dist: pandas (>=1.5.1,<2.0.0)
